polars_fastembed_cpu/__init__.py
polars_fastembed_cpu/libs/libonnxruntime.so
polars_fastembed_cpu/libs/libonnxruntime.so.1
polars_fastembed_cpu/libs/libonnxruntime.so.1.23.0
polars_fastembed_cpu/libs/libonnxruntime_providers_shared.so
polars_fastembed_cpu-0.1.17.dist-info/WHEEL
polars_fastembed_cpu-0.1.17.dist-info/METADATA
polars_fastembed_cpu-0.1.17.dist-info/RECORD
